lyrically/__init__.py
lyrically/config.py
lyrically/database/__init__.py
lyrically/database/initialize.py
lyrically/request/__init__.py
lyrically/utils/artist.py
lyrically/utils/errors.py
lyrically/utils/models.py
lyrically/utils/storage.py
lyrically-5.12.18.dist-info/METADATA
lyrically-5.12.18.dist-info/WHEEL
lyrically-5.12.18.dist-info/licenses/LICENSE
lyrically-5.12.18.dist-info/RECORD
