Metadata-Version: 2.4
Name: lyrically
Version: 5.12.18
Summary: An asynchronous Python client for fetching complete artist lyrical discographies from the web.
Project-URL: Homepage, https://github.com/filming/lyrically
Project-URL: Repository, https://github.com/filming/lyrically
Project-URL: Issues, https://github.com/filming/lyrically/issues
Project-URL: Changelog, https://github.com/filming/lyrically/blob/master/CHANGELOG.md
Author: Filming
License: MIT License
License-File: LICENSE
Keywords: async,azlyrics,lyrics,music,python,python3,scraping
Classifier: Development Status :: 3 - Alpha
Classifier: Intended Audience :: Developers
Classifier: License :: OSI Approved :: MIT License
Classifier: Programming Language :: Python :: 3
Classifier: Programming Language :: Python :: 3.10
Classifier: Programming Language :: Python :: 3.11
Classifier: Programming Language :: Python :: 3.12
Classifier: Programming Language :: Python :: 3.13
Requires-Python: >=3.10
Requires-Dist: aiohttp>=3.9.0
Requires-Dist: aiosqlite>=0.20.0
Requires-Dist: beautifulsoup4>=4.12.0
Requires-Dist: lxml>=5.0.0
Requires-Dist: platformdirs>=4.0.0
Provides-Extra: dev
Requires-Dist: commitizen>=4.8.3; extra == 'dev'
Requires-Dist: mypy>=1.16.1; extra == 'dev'
Requires-Dist: pre-commit>=4.2.0; extra == 'dev'
Requires-Dist: ruff>=0.12.1; extra == 'dev'
Requires-Dist: twine>=6.1.0; extra == 'dev'
